setup.py
docs/HISTORY.txt
src/mr/__init__.py
src/mr.parker.egg-info/PKG-INFO
src/mr.parker.egg-info/SOURCES.txt
src/mr.parker.egg-info/dependency_links.txt
src/mr.parker.egg-info/entry_points.txt
src/mr.parker.egg-info/namespace_packages.txt
src/mr.parker.egg-info/not-zip-safe
src/mr.parker.egg-info/requires.txt
src/mr.parker.egg-info/top_level.txt
src/mr/parker/README.txt
src/mr/parker/__init__.py
src/mr/parker/peter.py