Metadata-Version: 1.0
Name: mr.parker
Version: 1.0
Summary: Ensures that the PyPI bus factor for a package is above a certain threshold.
Home-page: http://dev.plone.org/collective/browser/mr.parker
Author: Matthew Wilkes
Author-email: matthew@matthewwilkes.co.uk
License: BSD
Platform: UNKNOWN
Classifier: Programming Language :: Python
Classifier: Programming Language :: Python :: 2.6
Classifier: Programming Language :: Python :: 3
Classifier: Development Status :: 3 - Alpha
Classifier: Environment :: Console
Classifier: Intended Audience :: Developers
Classifier: License :: OSI Approved :: BSD License
Classifier: Topic :: Software Development
Classifier: Topic :: System :: Software Distribution
Classifier: Topic :: Utilities
